qv_mcp_client/__init__.py
qv_mcp_client/client.py
qv_mcp_client/config.py
qv_mcp_client/exceptions.py
qv_mcp_client/manager.py
qv_mcp_client/utils.py
qv_mcp_client-0.1.0.dist-info/METADATA
qv_mcp_client-0.1.0.dist-info/WHEEL
qv_mcp_client-0.1.0.dist-info/licenses/LICENSE
qv_mcp_client-0.1.0.dist-info/RECORD
