Metadata-Version: 2.4
Name: qv-mcp-client
Version: 0.1.0
Summary: A Python client library for the Model Context Protocol (MCP) that provides clean, async connectivity to MCP servers
Project-URL: Homepage, https://www.quantyverse.ai
Project-URL: Documentation, https://github.com/quantyverse/qv-mcp-client#readme
Project-URL: Repository, https://github.com/quantyverse/qv-mcp-client
Project-URL: Issues, https://github.com/quantyverse/qv-mcp-client/issues
Author-email: Thomas Bernhard <thomas@quantyverse.com>
License: MIT
License-File: LICENSE
Keywords: ai,anthropic,async,claude,client,llm,mcp,model-context-protocol,quantyverse
Classifier: Development Status :: 4 - Beta
Classifier: Framework :: AsyncIO
Classifier: Intended Audience :: Developers
Classifier: License :: OSI Approved :: MIT License
Classifier: Operating System :: OS Independent
Classifier: Programming Language :: Python :: 3
Classifier: Programming Language :: Python :: 3.10
Classifier: Programming Language :: Python :: 3.11
Classifier: Programming Language :: Python :: 3.12
Classifier: Topic :: Scientific/Engineering :: Artificial Intelligence
Classifier: Topic :: Software Development :: Libraries :: Python Modules
Requires-Python: >=3.10
Requires-Dist: mcp>=1.9.1
